tw_cwa_weather_mcp/__init__.py
tw_cwa_weather_mcp/aliased.txt
tw_cwa_weather_mcp/app_mcp.py
tw_cwa_weather_mcp/counties.txt
tw_cwa_weather_mcp-1.0.0.dist-info/licenses/LICENSE
tw_cwa_weather_mcp-1.0.0.dist-info/METADATA
tw_cwa_weather_mcp-1.0.0.dist-info/WHEEL
tw_cwa_weather_mcp-1.0.0.dist-info/entry_points.txt
tw_cwa_weather_mcp-1.0.0.dist-info/top_level.txt
tw_cwa_weather_mcp-1.0.0.dist-info/RECORD
