Metadata-Version: 2.4
Name: tw-cwa-weather-mcp
Version: 1.0.0
Summary: Taiwan CWA Weather MCP Server - Access Taiwan weather data through Model Context Protocol
Author-email: nigue3025 <your-email@example.com>
License: MIT
Project-URL: Homepage, https://github.com/nigue3025/tw_cwa_weather_mcp
Project-URL: Repository, https://github.com/nigue3025/tw_cwa_weather_mcp
Project-URL: Issues, https://github.com/nigue3025/tw_cwa_weather_mcp/issues
Keywords: mcp,model-context-protocol,taiwan,weather,cwa
Classifier: Development Status :: 4 - Beta
Classifier: Intended Audience :: Developers
Classifier: License :: OSI Approved :: MIT License
Classifier: Programming Language :: Python :: 3
Classifier: Programming Language :: Python :: 3.10
Classifier: Programming Language :: Python :: 3.11
Classifier: Programming Language :: Python :: 3.12
Requires-Python: >=3.10
License-File: LICENSE
Requires-Dist: mcp>=1.0.0
Requires-Dist: requests>=2.32.0
Requires-Dist: pydantic>=2.0.0
Requires-Dist: httpx>=0.28.0
Dynamic: license-file
